bnr_exchangerate/__init__.py
bnr_exchangerate/admin.py
bnr_exchangerate/models.py
django_bnr_exchangerate-0.1.0.dist-info/DESCRIPTION.rst
django_bnr_exchangerate-0.1.0.dist-info/METADATA
django_bnr_exchangerate-0.1.0.dist-info/metadata.json
django_bnr_exchangerate-0.1.0.dist-info/RECORD
django_bnr_exchangerate-0.1.0.dist-info/top_level.txt
django_bnr_exchangerate-0.1.0.dist-info/WHEEL
