Metadata-Version: 2.0
Name: django-bnr-exchangerate
Version: 0.1.0
Summary: A django application to help with exchangerates from bnr.ro
Home-page: https://github.com/opencbsoft/django-bnr-exchangerate
Author: Cristian Boboc
Author-email: cristi@pidginhost.com
License: MIT
Keywords: exchangerate,bnr
Platform: UNKNOWN
Classifier: Development Status :: 3 - Alpha
Classifier: Intended Audience :: Developers
Classifier: Topic :: Software Development :: Libraries :: Python Modules
Classifier: License :: OSI Approved :: MIT License
Classifier: Programming Language :: Python :: 3
Classifier: Programming Language :: Python :: 3.2
Classifier: Programming Language :: Python :: 3.3
Classifier: Programming Language :: Python :: 3.4
